README
setup.py
bambu_ajax/__init__.py
bambu_ajax/sites.py
bambu_ajax/test_views.py
bambu_ajax/urls.py
bambu_ajax/views.py
bambu_ajax.egg-info/PKG-INFO
bambu_ajax.egg-info/SOURCES.txt
bambu_ajax.egg-info/dependency_links.txt
bambu_ajax.egg-info/requires.txt
bambu_ajax.egg-info/top_level.txt
bambu_ajax/templates/ajax/utils.js
bambu_ajax/templatetags/__init__.py
bambu_ajax/templatetags/ajax.py
bambu_ajax/test/__init__.py
bambu_ajax/test/ajax.py