Metadata-Version: 1.1
Name: bambu-ajax
Version: 2.0
Summary: AJAX utility functions for Django
Home-page: https://github.com/iamsteadman/bambu-ajax
Author: Steadman
Author-email: mark@steadman.io
License: UNKNOWN
Platform: UNKNOWN
Classifier: Development Status :: 4 - Beta
Classifier: Environment :: Web Environment
Classifier: Framework :: Django
